vanilla/__init__.py
vanilla/_version.py
vanilla/dialogs.py
vanilla/dragAndDrop.py
vanilla/nsSubclasses.py
vanilla/py23.py
vanilla/vanillaBase.py
vanilla/vanillaBox.py
vanilla/vanillaBrowser.py
vanilla/vanillaButton.py
vanilla/vanillaCheckBox.py
vanilla/vanillaColorWell.py
vanilla/vanillaComboBox.py
vanilla/vanillaDatePicker.py
vanilla/vanillaDrawer.py
vanilla/vanillaEditText.py
vanilla/vanillaGradientButton.py
vanilla/vanillaGridView.py
vanilla/vanillaGroup.py
vanilla/vanillaImageView.py
vanilla/vanillaLevelIndicator.py
vanilla/vanillaList.py
vanilla/vanillaList2.py
vanilla/vanillaMenuBuilder.py
vanilla/vanillaPathControl.py
vanilla/vanillaPopUpButton.py
vanilla/vanillaPopover.py
vanilla/vanillaProgressBar.py
vanilla/vanillaProgressSpinner.py
vanilla/vanillaRadioGroup.py
vanilla/vanillaScrollView.py
vanilla/vanillaSearchBox.py
vanilla/vanillaSegmentedButton.py
vanilla/vanillaSlider.py
vanilla/vanillaSplitView.py
vanilla/vanillaStackGroup.py
vanilla/vanillaStackView.py
vanilla/vanillaStepper.py
vanilla/vanillaTabs.py
vanilla/vanillaTextBox.py
vanilla/vanillaTextEditor.py
vanilla/vanillaWindows.py
vanilla/test/__init__.py
vanilla/test/testAll.py
vanilla/test/testDialogs.py
vanilla/test/testDragAndDrop.py
vanilla/test/testGeometry.py
vanilla/test/testGridView.py
vanilla/test/testSplitview.py
vanilla/test/testStackView.py
vanilla/test/testTools.py
vanilla/test/testWindowBindings.py
cocoa_vanilla-0.7.0.dist-info/METADATA
cocoa_vanilla-0.7.0.dist-info/WHEEL
cocoa_vanilla-0.7.0.dist-info/top_level.txt
cocoa_vanilla-0.7.0.dist-info/RECORD
