Metadata-Version: 2.2
Name: cocoa-vanilla
Version: 0.7.0
Summary: A Pythonic wrapper around Cocoa.
Home-page: https://github.com/robotools/vanilla
Author: Tal Leming
Author-email: tal@typesupply.com
Maintainer: Just van Rossum, Frederik Berlaen
Maintainer-email: justvanrossum@gmail.com
License: MIT
Platform: macOS
Requires-Python: >=3.6
Requires-Dist: pyobjc
Dynamic: author
Dynamic: author-email
Dynamic: description
Dynamic: description-content-type
Dynamic: home-page
Dynamic: license
Dynamic: maintainer
Dynamic: maintainer-email
Dynamic: platform
Dynamic: requires-dist
Dynamic: requires-python
Dynamic: summary
